oarepo_s3/__init__.py
oarepo_s3/api.py
oarepo_s3/config.py
oarepo_s3/constants.py
oarepo_s3/ext.py
oarepo_s3/proxies.py
oarepo_s3/s3.py
oarepo_s3/signals.py
oarepo_s3/storage.py
oarepo_s3/tasks.py
oarepo_s3/views.py
tests/__init__.py
tests/conftest.py
tests/helpers.py
tests/test_api.py
tests/test_drafts.py
tests/test_storage.py
tests/test_tasks.py
tests/utils.py
oarepo_s3-1.4.5.dist-info/AUTHORS.rst
oarepo_s3-1.4.5.dist-info/LICENSE
oarepo_s3-1.4.5.dist-info/METADATA
oarepo_s3-1.4.5.dist-info/WHEEL
oarepo_s3-1.4.5.dist-info/entry_points.txt
oarepo_s3-1.4.5.dist-info/top_level.txt
oarepo_s3-1.4.5.dist-info/RECORD
