Metadata-Version: 2.1
Name: oarepo-s3
Version: 1.4.5
Summary: S3 file storage support for Invenio.
Home-page: https://github.com/oarepo/oarepo-s3
License: UNKNOWN
Platform: any
Classifier: Development Status :: 5 - Production/Stable
Requires-Python: >=3.6
License-File: LICENSE
License-File: AUTHORS.rst
Requires-Dist: invenio-s3 (==1.0.3)
Provides-Extra: tests
Requires-Dist: moto[s3] (>=1.3.16) ; extra == 'tests'
Requires-Dist: oarepo-records-draft (>=5.5.8) ; extra == 'tests'
Requires-Dist: oarepo[tests] (<3.4.0,>=3.3.0) ; extra == 'tests'
Requires-Dist: mock (>=4.0.3) ; extra == 'tests'
